README
setup.py
EvidentialToolBus.egg-info/PKG-INFO
EvidentialToolBus.egg-info/SOURCES.txt
EvidentialToolBus.egg-info/dependency_links.txt
EvidentialToolBus.egg-info/entry_points.txt
EvidentialToolBus.egg-info/requires.txt
EvidentialToolBus.egg-info/top_level.txt
etb/__init__.py
etb/etb.py
etb/etbclientlib.py
etb/etbconfig.py
etb/etbd.py
etb/etbsh.py
etb/git_interface.py
etb/interpret_state.py
etb/networking.py
etb/parser.py
etb/terms.py
etb/utils.py
etb/wrapper.py
etb/datalog/__init__.py
etb/datalog/engine.py
etb/datalog/externals.py
etb/datalog/graph.py
etb/datalog/index.py
etb/datalog/inference.py
etb/datalog/model.py
etb/datalog/test/__init__.py
etb/datalog/test/engine_test.py
etb/datalog/test/externals_test.py
etb/datalog/test/graph_test.py
etb/datalog/test/index_test.py
etb/datalog/test/inference_test.py
etb/datalog/test/model_test.py
etb/wrappers/__init__.py
etb/wrappers/builtins.py
proxyland/__init__.py
proxyland/config.py
proxyland/confirm.py
proxyland/daemon.py
proxyland/etbdaemon.py
proxyland/log.py
proxyland/proxy.py
proxyland/register.py
proxyland/resource.py
proxyland/spawn.py
proxyland/sqlite.py
proxyland/utils.py