Metadata-Version: 1.1
Name: EvidentialToolBus
Version: 1.0.1
Summary: The Evidential Tool Bus.
Home-page: http://pypi.python.org/pypi/ETB/
Author: Simon Cruanes, Gregoire Hamon, Stijn Heymans, Ian Mason, Sam Owre, N. Shankar
Author-email: owre@csl.sri.com
License: LICENSE
Platform: UNKNOWN
Classifier: Development Status :: 3 - Alpha
Classifier: Natural Language :: English
Classifier: License :: OSI Approved :: GNU General Public License (GPL)
Classifier: Operating System :: OS Independent
Classifier: Programming Language :: Python
Classifier: Programming Language :: Python :: 2
Classifier: Programming Language :: Python :: 2.6
Classifier: Programming Language :: Python :: 2.7
